ramachandraw/__init__.py
ramachandraw/exceptions.py
ramachandraw/kde.dat
ramachandraw/parser.py
ramachandraw/py.typed
ramachandraw/utils.py
ramachandraw-1.0.1.dist-info/LICENSE
ramachandraw-1.0.1.dist-info/METADATA
ramachandraw-1.0.1.dist-info/WHEEL
ramachandraw-1.0.1.dist-info/RECORD
