Metadata-Version: 2.1
Name: ramachandraw
Version: 1.0.1
Summary: Ramachandran plotting tool
License: MIT
Author: Alexandre Cirilo
Author-email: 38657258+alxdrcirilo@users.noreply.github.com
Requires-Python: >=3.9,<4.0
Classifier: License :: OSI Approved :: MIT License
Classifier: Programming Language :: Python :: 3
Classifier: Programming Language :: Python :: 3.9
Classifier: Programming Language :: Python :: 3.10
Classifier: Programming Language :: Python :: 3.11
Classifier: Programming Language :: Python :: 3.12
Requires-Dist: biopython (>=1.83,<2.0)
Requires-Dist: matplotlib (>=3.8.3,<4.0.0)
